autonomous_robotic_sample_handling/plugin_config.yml
autonomous_robotic_sample_handling/API/ThorLabs.MotionControl.Benchtop.DCServoCLI.dll
autonomous_robotic_sample_handling/API/ThorLabs.MotionControl.Benchtop.PrecisionPiezoCLI.dll
autonomous_robotic_sample_handling/API/ThorLabs.MotionControl.KCube.DCServoCLI.dll
autonomous_robotic_sample_handling/API/ThorLabs.MotionControl.KCube.LaserDiodeCLI.dll
autonomous_robotic_sample_handling/API/ThorLabs.MotionControl.KCube.LaserSourceCLI.dll
autonomous_robotic_sample_handling/API/ThorLabs.MotionControl.KCube.PositionAlignerCLI.dll
autonomous_robotic_sample_handling/API/ThorLabs.MotionControl.KCube.StrainGaugeCLI.dll
autonomous_robotic_sample_handling/API/ThorLabs.MotionControl.PolarizerCLI.dll
autonomous_robotic_sample_handling/API/ThorLabs.MotionControl.TCube.InertialMotorCLI.dll
autonomous_robotic_sample_handling/API/ThorLabs.MotionControl.TDIEngineCLI.dll
autonomous_robotic_sample_handling/API/ThorLabs.MotionControl.VerticalStageCLI.dll
autonomous_robotic_sample_handling/API/Thorlabs.APT.dll
autonomous_robotic_sample_handling/API/Thorlabs.MotionControl.Benchtop.BrushlessMotor.dll
autonomous_robotic_sample_handling/API/Thorlabs.MotionControl.Benchtop.BrushlessMotorCLI.dll
autonomous_robotic_sample_handling/API/Thorlabs.MotionControl.Benchtop.BrushlessMotorUI.dll
autonomous_robotic_sample_handling/API/Thorlabs.MotionControl.Benchtop.DCServo.dll
autonomous_robotic_sample_handling/API/Thorlabs.MotionControl.Benchtop.DCServoUI.dll
autonomous_robotic_sample_handling/API/Thorlabs.MotionControl.Benchtop.NanoTrak.dll
autonomous_robotic_sample_handling/API/Thorlabs.MotionControl.Benchtop.NanoTrakCLI.dll
autonomous_robotic_sample_handling/API/Thorlabs.MotionControl.Benchtop.NanoTrakUI.dll
autonomous_robotic_sample_handling/API/Thorlabs.MotionControl.Benchtop.Piezo.dll
autonomous_robotic_sample_handling/API/Thorlabs.MotionControl.Benchtop.PiezoCLI.dll
autonomous_robotic_sample_handling/API/Thorlabs.MotionControl.Benchtop.PiezoUI.dll
navigate_at_scale-0.0.0.dist-info/LICENSE
navigate_at_scale-0.0.0.dist-info/METADATA
navigate_at_scale-0.0.0.dist-info/WHEEL
navigate_at_scale-0.0.0.dist-info/entry_points.txt
navigate_at_scale-0.0.0.dist-info/top_level.txt
navigate_at_scale-0.0.0.dist-info/RECORD
